mauve_client/__init__.py
mauve_client/api_client.py
mauve_client/configuration.py
mauve_client/rest.py
mauve_client/api/__init__.py
mauve_client/api/categories_api.py
mauve_client/api/customers_api.py
mauve_client/api/documents_api.py
mauve_client/api/orders_api.py
mauve_client/api/others_api.py
mauve_client/api/portal__categories_api.py
mauve_client/api/portal__documents_api.py
mauve_client/api/portal__orders_api.py
mauve_client/api/portal__products_api.py
mauve_client/api/products_api.py
mauve_client/models/__init__.py
mauve_client/models/abda_artikelstamm.py
mauve_client/models/abda_other_pack_size.py
mauve_client/models/abdata_laiendaten.py
mauve_client/models/availibity.py
mauve_client/models/bundle_item.py
mauve_client/models/category.py
mauve_client/models/category_translation.py
mauve_client/models/content_unit.py
mauve_client/models/courier_service_slot.py
mauve_client/models/create_customer_request.py
mauve_client/models/create_customer_response.py
mauve_client/models/create_document_line_request.py
mauve_client/models/create_document_parcel_label_request.py
mauve_client/models/create_document_payment_request.py
mauve_client/models/create_order_payment_request.py
mauve_client/models/create_order_payment_response.py
mauve_client/models/create_order_prescription_image_request.py
mauve_client/models/create_order_prescription_image_response.py
mauve_client/models/create_order_request.py
mauve_client/models/create_order_response.py
mauve_client/models/create_portal_document_payment_request.py
mauve_client/models/create_portal_document_payment_response.py
mauve_client/models/create_portal_order_payment_request.py
mauve_client/models/create_portal_order_payment_response.py
mauve_client/models/create_portal_order_prescription_image_request.py
mauve_client/models/create_portal_order_prescription_image_response.py
mauve_client/models/create_portal_order_request.py
mauve_client/models/create_portal_order_response.py
mauve_client/models/customer.py
mauve_client-0.1.0.dist-info/METADATA
mauve_client-0.1.0.dist-info/WHEEL
mauve_client-0.1.0.dist-info/top_level.txt
mauve_client-0.1.0.dist-info/RECORD
