Metadata-Version: 2.4
Name: mauve-client
Version: 0.1.0
Summary: Mauve Admin API
Home-page: 
Author-email: 
Keywords: Swagger,Mauve Admin API
Requires-Dist: urllib3>=1.15
Requires-Dist: six>=1.10
Requires-Dist: certifi
Requires-Dist: python-dateutil
Dynamic: description
Dynamic: keywords
Dynamic: requires-dist
Dynamic: summary
